luna/pathology/__init__.py
luna/pathology/analysis/__init__.py
luna/pathology/analysis/ml.py
luna/pathology/cli/__init__.py
luna/pathology/cli/dsa_annotation_etl.py
luna/pathology/cli/dsa_upload.py
luna/pathology/cli/dsa_viz.py
luna/pathology/cli/extract_kfunction_statistics.py
luna/pathology/cli/extract_shape_features.py
luna/pathology/cli/extract_stain_texture.py
luna/pathology/cli/extract_tile_statistics.py
luna/pathology/cli/generate_mask.py
luna/pathology/cli/generate_tile_labels.py
luna/pathology/cli/generate_tile_mask.py
luna/pathology/cli/generate_tiles.py
luna/pathology/cli/infer_tile_labels.py
luna/pathology/cli/run_stardist_cell_detection.py
luna/pathology/cli/run_tissue_detection.py
luna/pathology/cli/save_tiles.py
luna/pathology/cli/slide_etl.py
luna/pathology/cli/train_tissue_classifier.py
luna/pathology/cli/visualize_tile_labels_png.py
luna/pathology/cli/examples/example_bitmask_polygon_config.yaml
luna/pathology/cli/examples/example_bmp_polygon_config.yml
luna/pathology/cli/examples/example_dsa_upload_config.yaml
luna/pathology/cli/examples/example_heatmap_config.yaml
luna/pathology/cli/examples/example_qupath_polygon_config.yaml
luna/pathology/cli/examples/example_regional_polygon_config.yaml
luna/pathology/cli/examples/example_stardist_cell_config.yaml
luna/pathology/cli/examples/example_stardist_polygon_config.yaml
luna/pathology/cli/examples/generate_tile_labels_no_labels.yaml
luna/pathology/cli/examples/generate_tile_labels_with_ov_labels.yaml
luna/pathology/cli/examples/visualize_model_inference.yaml
luna/pathology/common/__init__.py
luna/pathology/common/annotation_utils.py
luna/pathology/common/build_geojson.py
luna/pathology/common/schemas.py
luna/pathology/common/slideviewer_client.py
luna/pathology/common/utils.py
luna/pathology/dsa/__init__.py
luna/pathology/dsa/dsa_api_handler.py
luna/pathology/dsa/utils.py
luna/pathology/examples/extract_feature_vectors.py
luna/pathology/slideviewer/__init__.py
pyluna_pathology-0.3.3.dist-info/METADATA
pyluna_pathology-0.3.3.dist-info/WHEEL
pyluna_pathology-0.3.3.dist-info/entry_points.txt
pyluna_pathology-0.3.3.dist-info/top_level.txt
pyluna_pathology-0.3.3.dist-info/zip-safe
pyluna_pathology-0.3.3.dist-info/RECORD
