Metadata-Version: 2.1
Name: pyluna-pathology
Version: 0.3.3
Summary: Transformation functions and services for multi-modal oncology data
Home-page: https://componcmsk.org/msk-mind/
Author: msk-mind
Author-email: CompOncBST@mskcc.org
License: Apache License version 2.0
Project-URL: Bug Tracker, https://github.com/msk-mind/luna/issues
Keywords: radiology,pathology,clinical
Platform: UNKNOWN
Classifier: Framework :: Pytest
Classifier: Development Status :: 3 - Alpha
Classifier: License :: OSI Approved :: Apache Software License
Classifier: Operating System :: OS Independent
Classifier: Programming Language :: Python :: 3
Classifier: Programming Language :: Python :: 3.6
Classifier: Programming Language :: Python :: 3.7
Classifier: Topic :: Scientific/Engineering :: Artificial Intelligence
Requires-Dist: pyluna-common
Requires-Dist: openslide-python
Requires-Dist: torch
Requires-Dist: torchmetrics
Requires-Dist: torchvision
Requires-Dist: staintools
Requires-Dist: tqdm
Requires-Dist: pyradiomics
Requires-Dist: itk
Requires-Dist: shapely
Requires-Dist: seaborn
Requires-Dist: ijson
Requires-Dist: geojson
Requires-Dist: orjson
Requires-Dist: scikit-learn
Requires-Dist: scikit-image
Requires-Dist: opencv-python
Requires-Dist: girder-client
Requires-Dist: spams
Requires-Dist: h5py
Requires-Dist: ray
Requires-Dist: docker
Provides-Extra: dev
Requires-Dist: pytest ; extra == 'dev'
Requires-Dist: pytest-cov ; extra == 'dev'
Requires-Dist: pytest-mock ; extra == 'dev'
Requires-Dist: pytest-runner ; extra == 'dev'
Requires-Dist: testfixtures ; extra == 'dev'
Requires-Dist: requests-mock ; extra == 'dev'
Requires-Dist: mock ; extra == 'dev'
Requires-Dist: wheel (>=0.22) ; extra == 'dev'
Requires-Dist: pyinstaller (>=4.0) ; extra == 'dev'
Requires-Dist: poetry ; extra == 'dev'
Requires-Dist: python-semantic-release ; extra == 'dev'
Requires-Dist: m2r2 ; extra == 'dev'
Requires-Dist: twine ; extra == 'dev'
Requires-Dist: Sphinx ; extra == 'dev'
